timeseries_store_sale/__init__.py
timeseries_store_sale/data/__init__.py
timeseries_store_sale/data/generate_dataloader.py
timeseries_store_sale/data/predict_dataloader.py
timeseries_store_sale/data/preprocessing.py
timeseries_store_sale/model/__init__.py
timeseries_store_sale/model/train.py
timeseries_store_sale-0.1.50.dist-info/LICENSE
timeseries_store_sale-0.1.50.dist-info/METADATA
timeseries_store_sale-0.1.50.dist-info/WHEEL
timeseries_store_sale-0.1.50.dist-info/top_level.txt
timeseries_store_sale-0.1.50.dist-info/RECORD
