Metadata-Version: 2.1
Name: timeseries-store-sale
Version: 0.1.50
Summary: time series model for training sequence dataset
Home-page: https://doc.com
Author: ZhangLe
Author-email: zhanglenlp@gmail.com
Project-URL: Bug Tracker, https://doc.com
Classifier: Programming Language :: Python :: 3
Classifier: License :: OSI Approved :: MIT License
Classifier: Operating System :: OS Independent
Requires-Python: >=3.6
License-File: LICENSE
Requires-Dist: torch (>=1.6.0)
Requires-Dist: pandas (>=1.3.5)
Requires-Dist: numpy (>=1.21.5)
Requires-Dist: DateTime (>=4.4)
Requires-Dist: xgboost (>=1.2.0)
Requires-Dist: scikit-learn (>=1.0.2)
Requires-Dist: keras-tcn (>=3.4.0)
Requires-Dist: ngboost (>=0.3.13)
Requires-Dist: statsmodels (>=0.13.5)
Requires-Dist: matplotlib (>=3.1.1)
Requires-Dist: pickleshare (>=0.7.5)
Requires-Dist: cloudpickle (>=1.2.2)
Requires-Dist: optuna (>=2.10.0)
